{
  "versionInfo": {
    "ROM DataFile JSON Version": "1.0"
  },
  "romdata": [
    {
      "name": "Pirate 2 (061005 World)",
      "mameName": "pirate2",
      "path": "{gamesDir}\\MAME\\ROMS\\pirate2.7z",
      "emulatorName": "Mame64 Win32",
      "companyName": "Igrosoft",
      "year": "2006",
      "gameType": "Casino / Reels",
      "language": "English",
      "comment": "good",
      "timesPlayed": "0",
      "paramMode": "1",
      "players": "1P"
    },
    {
      "name": "Pirate 2 (070126 Russia)",
      "mameName": "pirate2_2",
      "parentName": "pirate2",
      "path": "{gamesDir}\\MAME\\ROMS\\pirate2.7z",
      "emulatorName": "Mame64 Win32",
      "companyName": "Igrosoft",
      "year": "2006",
      "gameType": "Casino / Reels",
      "language": "English",
      "comment": "good",
      "timesPlayed": "0",
      "paramMode": "1",
      "players": "1P"
    },
    {
      "name": "Pirate 2 (bootleg, 070126, banking address hack)",
      "mameName": "pirate2_2a",
      "parentName": "pirate2",
      "path": "{gamesDir}\\MAME\\ROMS\\pirate2.7z",
      "emulatorName": "Mame64 Win32",
      "companyName": "bootleg",
      "year": "2006",
      "gameType": "Casino / Reels",
      "language": "English",
      "comment": "good",
      "timesPlayed": "0",
      "paramMode": "1",
      "players": "1P"
    },
    {
      "name": "Pirate 2 (090528 Lottery)",
      "mameName": "pirate2_3",
      "parentName": "pirate2",
      "path": "{gamesDir}\\MAME\\ROMS\\pirate2.7z",
      "emulatorName": "Mame64 Win32",
      "companyName": "Igrosoft",
      "year": "2006",
      "gameType": "Casino / Reels",
      "language": "English",
      "comment": "good",
      "timesPlayed": "0",
      "paramMode": "1",
      "players": "1P"
    },
    {
      "name": "Pirate 2 (090730 Entertainment)",
      "mameName": "pirate2_4",
      "parentName": "pirate2",
      "path": "{gamesDir}\\MAME\\ROMS\\pirate2.7z",
      "emulatorName": "Mame64 Win32",
      "companyName": "Igrosoft",
      "year": "2006",
      "gameType": "Casino / Reels",
      "language": "English",
      "comment": "good",
      "timesPlayed": "0",
      "paramMode": "1",
      "players": "1P"
    },
    {
      "name": "Pirate 2 (bootleg, 061005, banking address hack set 1)",
      "mameName": "pirate2a",
      "parentName": "pirate2",
      "path": "{gamesDir}\\MAME\\ROMS\\pirate2.7z",
      "emulatorName": "Mame64 Win32",
      "companyName": "bootleg",
      "year": "2006",
      "gameType": "Casino / Reels",
      "language": "English",
      "comment": "good",
      "timesPlayed": "0",
      "paramMode": "1",
      "players": "1P"
    },
    {
      "name": "Pirate 2 (bootleg, 061005, banking address hack set 2)",
      "mameName": "pirate2b",
      "parentName": "pirate2",
      "path": "{gamesDir}\\MAME\\ROMS\\pirate2.7z",
      "emulatorName": "Mame64 Win32",
      "companyName": "bootleg",
      "year": "2006",
      "gameType": "Casino / Reels",
      "language": "English",
      "comment": "good",
      "timesPlayed": "0",
      "paramMode": "1",
      "players": "1P"
    },
    {
      "name": "Pirate 2 (bootleg, 061005, banking address hack, changed version text set 1)",
      "mameName": "pirate2c",
      "parentName": "pirate2",
      "path": "{gamesDir}\\MAME\\ROMS\\pirate2.7z",
      "emulatorName": "Mame64 Win32",
      "companyName": "bootleg",
      "year": "2006",
      "gameType": "Casino / Reels",
      "language": "English",
      "comment": "good",
      "timesPlayed": "0",
      "paramMode": "1",
      "players": "1P"
    },
    {
      "name": "Pirate 2 (bootleg, 061005, banking address hack, changed version text set 2)",
      "mameName": "pirate2d",
      "parentName": "pirate2",
      "path": "{gamesDir}\\MAME\\ROMS\\pirate2.7z",
      "emulatorName": "Mame64 Win32",
      "companyName": "bootleg",
      "year": "2006",
      "gameType": "Casino / Reels",
      "language": "English",
      "comment": "good",
      "timesPlayed": "0",
      "paramMode": "1",
      "players": "1P"
    },
    {
      "name": "Pirate 2 (bootleg, 061005, banking address hack, changed version text set 3)",
      "mameName": "pirate2e",
      "parentName": "pirate2",
      "path": "{gamesDir}\\MAME\\ROMS\\pirate2.7z",
      "emulatorName": "Mame64 Win32",
      "companyName": "bootleg",
      "year": "2006",
      "gameType": "Casino / Reels",
      "language": "English",
      "comment": "good",
      "timesPlayed": "0",
      "paramMode": "1",
      "players": "1P"
    },
    {
      "name": "Pirate 2 (bootleg, 061005, VIDEO GAME-1 PR01)",
      "mameName": "pirate2f",
      "parentName": "pirate2",
      "path": "{gamesDir}\\MAME\\ROMS\\pirate2.7z",
      "emulatorName": "Mame64 Win32",
      "companyName": "bootleg",
      "year": "2006",
      "gameType": "Casino / Reels",
      "language": "Russian",
      "comment": "good",
      "timesPlayed": "0",
      "paramMode": "1",
      "players": "1P"
    },
    {
      "name": "Pirate 2 (bootleg, 061005, LOTTOGAME (I))",
      "mameName": "pirate2g",
      "parentName": "pirate2",
      "path": "{gamesDir}\\MAME\\ROMS\\pirate2.7z",
      "emulatorName": "Mame64 Win32",
      "companyName": "bootleg",
      "year": "2006",
      "gameType": "Casino / Reels",
      "language": "Russian",
      "comment": "good",
      "timesPlayed": "0",
      "paramMode": "1",
      "players": "1P"
    },
    {
      "name": "Pirate 2 (bootleg, 061005, LOTOS PR01)",
      "mameName": "pirate2h",
      "parentName": "pirate2",
      "path": "{gamesDir}\\MAME\\ROMS\\pirate2.7z",
      "emulatorName": "Mame64 Win32",
      "companyName": "bootleg",
      "year": "2006",
      "gameType": "Casino / Reels",
      "language": "Russian",
      "comment": "good",
      "timesPlayed": "0",
      "paramMode": "1",
      "players": "1P"
    },
    {
      "name": "Pirate (060210 World)",
      "mameName": "pirate_2",
      "parentName": "pirate_3",
      "path": "{gamesDir}\\MAME\\ROMS\\pirate_3.7z",
      "emulatorName": "Mame64 Win32",
      "companyName": "Igrosoft",
      "year": "2005",
      "gameType": "Casino / Reels",
      "language": "English",
      "comment": "good",
      "timesPlayed": "0",
      "paramMode": "1",
      "players": "1P"
    },
    {
      "name": "Pirate (060803 World)",
      "mameName": "pirate_3",
      "path": "{gamesDir}\\MAME\\ROMS\\pirate_3.7z",
      "emulatorName": "Mame64 Win32",
      "companyName": "Igrosoft",
      "year": "2005",
      "gameType": "Casino / Reels",
      "language": "English",
      "comment": "good",
      "timesPlayed": "0",
      "paramMode": "1",
      "players": "1P"
    },
    {
      "name": "Pirate (070412 Russia)",
      "mameName": "pirate_4",
      "parentName": "pirate_3",
      "path": "{gamesDir}\\MAME\\ROMS\\pirate_3.7z",
      "emulatorName": "Mame64 Win32",
      "companyName": "Igrosoft",
      "year": "2005",
      "gameType": "Casino / Reels",
      "language": "English",
      "comment": "good",
      "timesPlayed": "0",
      "paramMode": "1",
      "players": "1P"
    }
  ]
}