{
  "versionInfo": {
    "ROM DataFile JSON Version": "1.0"
  },
  "romdata": [
    {
      "name": "FixEight (Europe)",
      "mameName": "fixeight",
      "path": "{gamesDir}\\MAME\\ROMS\\fixeight.7z",
      "emulatorName": "Mame64 Win32",
      "companyName": "Toaplan",
      "year": "1992",
      "gameType": "Shooter / Walking",
      "rating": "60 to 70 (Passable)",
      "language": "English",
      "comment": "good",
      "timesPlayed": "0",
      "paramMode": "1",
      "players": "3P sim"
    },
    {
      "name": "Out Zone",
      "mameName": "outzone",
      "path": "{gamesDir}\\MAME\\ROMS\\outzone.7z",
      "emulatorName": "Mame64 Win32",
      "companyName": "Toaplan",
      "year": "1990",
      "gameType": "Shooter / Walking",
      "rating": "70 to 80 (Good)",
      "language": "English",
      "comment": "good",
      "timesPlayed": "0",
      "paramMode": "1",
      "players": "2P sim"
    }
  ]
}