{
  "versionInfo": {
    "ROM DataFile JSON Version": "1.0"
  },
  "romdata": [
    {
      "name": "Buster Bros. (USA)",
      "mameName": "bbros",
      "parentName": "pang",
      "path": "{gamesDir}\\MAME\\ROMS\\pang.7z",
      "emulatorName": "Mame64 Win32",
      "companyName": "Mitchell (Capcom license)",
      "year": "1989",
      "gameType": "Shooter / 3rd Person",
      "language": "English",
      "comment": "good",
      "timesPlayed": "0",
      "paramMode": "1",
      "players": "2P sim"
    },
    {
      "name": "Mighty! Pang (Euro 001010)",
      "mameName": "mpang",
      "path": "{gamesDir}\\MAME\\ROMS\\mpang.7z",
      "emulatorName": "Mame64 Win32",
      "companyName": "Mitchell (Capcom license)",
      "year": "2000",
      "gameType": "Shooter / 3rd Person",
      "rating": "90 to 100 (Best Games)",
      "language": "English",
      "comment": "good",
      "timesPlayed": "0",
      "paramMode": "1",
      "players": "2P sim"
    },
    {
      "name": "Mighty! Pang (Japan 001011)",
      "mameName": "mpangj",
      "parentName": "mpang",
      "path": "{gamesDir}\\MAME\\ROMS\\mpang.7z",
      "emulatorName": "Mame64 Win32",
      "companyName": "Mitchell (Capcom license)",
      "year": "2000",
      "gameType": "Shooter / 3rd Person",
      "language": "Japanese",
      "comment": "good",
      "timesPlayed": "0",
      "paramMode": "1",
      "players": "2P sim"
    },
    {
      "name": "Mighty! Pang (Euro 000925)",
      "mameName": "mpangr1",
      "parentName": "mpang",
      "path": "{gamesDir}\\MAME\\ROMS\\mpang.7z",
      "emulatorName": "Mame64 Win32",
      "companyName": "Mitchell (Capcom license)",
      "year": "2000",
      "gameType": "Shooter / 3rd Person",
      "language": "English",
      "comment": "good",
      "timesPlayed": "0",
      "paramMode": "1",
      "players": "2P sim"
    },
    {
      "name": "Mighty! Pang (USA 001010)",
      "mameName": "mpangu",
      "parentName": "mpang",
      "path": "{gamesDir}\\MAME\\ROMS\\mpang.7z",
      "emulatorName": "Mame64 Win32",
      "companyName": "Mitchell (Capcom license)",
      "year": "2000",
      "gameType": "Shooter / 3rd Person",
      "language": "English",
      "comment": "good",
      "timesPlayed": "0",
      "paramMode": "1",
      "players": "2P sim"
    },
    {
      "name": "Pang (World)",
      "mameName": "pang",
      "path": "{gamesDir}\\MAME\\ROMS\\pang.7z",
      "emulatorName": "Mame64 Win32",
      "companyName": "Mitchell",
      "year": "1989",
      "gameType": "Shooter / 3rd Person",
      "rating": "90 to 100 (Best Games)",
      "language": "English",
      "comment": "good",
      "timesPlayed": "0",
      "paramMode": "1",
      "players": "2P sim"
    },
    {
      "name": "Pang! 3 (Euro 950601)",
      "mameName": "pang3",
      "path": "{gamesDir}\\MAME\\ROMS\\pang3.7z",
      "emulatorName": "Mame64 Win32",
      "companyName": "Mitchell",
      "year": "1995",
      "gameType": "Shooter / 3rd Person",
      "rating": "90 to 100 (Best Games)",
      "language": "English",
      "comment": "good",
      "timesPlayed": "0",
      "paramMode": "1",
      "players": "2P sim"
    },
    {
      "name": "Pang! 3 (bootleg)",
      "mameName": "pang3b",
      "parentName": "pang3",
      "path": "{gamesDir}\\MAME\\ROMS\\pang3.7z",
      "emulatorName": "Mame64 Win32",
      "companyName": "bootleg",
      "year": "1995",
      "gameType": "Shooter / 3rd Person",
      "language": "English",
      "comment": "good",
      "timesPlayed": "0",
      "paramMode": "1",
      "players": "2P sim"
    },
    {
      "name": "Pang! 3: Kaitou Tachi no Karei na Gogo (Japan 950511)",
      "mameName": "pang3j",
      "parentName": "pang3",
      "path": "{gamesDir}\\MAME\\ROMS\\pang3.7z",
      "emulatorName": "Mame64 Win32",
      "companyName": "Mitchell",
      "year": "1995",
      "gameType": "Shooter / 3rd Person",
      "language": "Japanese",
      "comment": "good",
      "timesPlayed": "0",
      "paramMode": "1",
      "players": "2P sim"
    },
    {
      "name": "Pang! 3 (Euro 950511)",
      "mameName": "pang3r1",
      "parentName": "pang3",
      "path": "{gamesDir}\\MAME\\ROMS\\pang3.7z",
      "emulatorName": "Mame64 Win32",
      "companyName": "Mitchell",
      "year": "1995",
      "gameType": "Shooter / 3rd Person",
      "language": "English",
      "comment": "good",
      "timesPlayed": "0",
      "paramMode": "1",
      "players": "2P sim"
    },
    {
      "name": "Pang (bootleg, set 1)",
      "mameName": "pangb",
      "parentName": "pang",
      "path": "{gamesDir}\\MAME\\ROMS\\pang.7z",
      "emulatorName": "Mame64 Win32",
      "companyName": "bootleg",
      "year": "1989",
      "gameType": "Shooter / 3rd Person",
      "language": "English",
      "comment": "good",
      "timesPlayed": "0",
      "paramMode": "1",
      "players": "2P sim"
    },
    {
      "name": "Pang (bootleg, set 4)",
      "mameName": "pangb2",
      "parentName": "pang",
      "path": "{gamesDir}\\MAME\\ROMS\\pang.7z",
      "emulatorName": "Mame64 Win32",
      "companyName": "bootleg",
      "year": "1989",
      "gameType": "Shooter / 3rd Person",
      "language": "English",
      "comment": "good",
      "timesPlayed": "0",
      "paramMode": "1",
      "players": "2P sim"
    },
    {
      "name": "Pang (bootleg, set 3)",
      "mameName": "pangba",
      "parentName": "pang",
      "path": "{gamesDir}\\MAME\\ROMS\\pang.7z",
      "emulatorName": "Mame64 Win32",
      "companyName": "bootleg",
      "year": "1989",
      "gameType": "Shooter / 3rd Person",
      "language": "English",
      "comment": "imperfect",
      "timesPlayed": "0",
      "paramMode": "1",
      "players": "2P sim"
    },
    {
      "name": "Pang (bootleg, set 5)",
      "mameName": "pangbb",
      "parentName": "pang",
      "path": "{gamesDir}\\MAME\\ROMS\\pang.7z",
      "emulatorName": "Mame64 Win32",
      "companyName": "bootleg",
      "year": "1989",
      "gameType": "Shooter / 3rd Person",
      "language": "English",
      "comment": "imperfect",
      "timesPlayed": "0",
      "paramMode": "1",
      "players": "2P sim"
    },
    {
      "name": "Pang (bootleg, set 2)",
      "mameName": "pangbold",
      "parentName": "pang",
      "path": "{gamesDir}\\MAME\\ROMS\\pang.7z",
      "emulatorName": "Mame64 Win32",
      "companyName": "bootleg",
      "year": "1989",
      "gameType": "Shooter / 3rd Person",
      "language": "English",
      "comment": "good",
      "timesPlayed": "0",
      "paramMode": "1",
      "players": "2P sim"
    },
    {
      "name": "Pomping World (Japan)",
      "mameName": "pompingw",
      "parentName": "pang",
      "path": "{gamesDir}\\MAME\\ROMS\\pang.7z",
      "emulatorName": "Mame64 Win32",
      "companyName": "Mitchell",
      "year": "1989",
      "gameType": "Shooter / 3rd Person",
      "language": "Japanese",
      "comment": "good",
      "timesPlayed": "0",
      "paramMode": "1",
      "players": "2P sim"
    },
    {
      "name": "Super Buster Bros. (USA 901001)",
      "mameName": "sbbros",
      "parentName": "spang",
      "path": "{gamesDir}\\MAME\\ROMS\\spang.7z",
      "emulatorName": "Mame64 Win32",
      "companyName": "Mitchell (Capcom license)",
      "year": "1990",
      "gameType": "Shooter / 3rd Person",
      "language": "English",
      "comment": "good",
      "timesPlayed": "0",
      "paramMode": "1",
      "players": "2P sim"
    },
    {
      "name": "Super Pang (World 900914)",
      "mameName": "spang",
      "path": "{gamesDir}\\MAME\\ROMS\\spang.7z",
      "emulatorName": "Mame64 Win32",
      "companyName": "Mitchell",
      "year": "1990",
      "gameType": "Shooter / 3rd Person",
      "rating": "90 to 100 (Best Games)",
      "language": "English",
      "comment": "good",
      "timesPlayed": "0",
      "paramMode": "1",
      "players": "2P sim"
    },
    {
      "name": "Super Pang (World 900914, bootleg)",
      "mameName": "spangbl",
      "parentName": "spang",
      "path": "{gamesDir}\\MAME\\ROMS\\spang.7z",
      "emulatorName": "Mame64 Win32",
      "companyName": "bootleg",
      "year": "1990",
      "gameType": "Shooter / 3rd Person",
      "language": "English",
      "comment": "imperfect",
      "timesPlayed": "0",
      "paramMode": "1",
      "players": "2P sim"
    },
    {
      "name": "Super Pang (Japan 901023)",
      "mameName": "spangj",
      "parentName": "spang",
      "path": "{gamesDir}\\MAME\\ROMS\\spang.7z",
      "emulatorName": "Mame64 Win32",
      "companyName": "Mitchell",
      "year": "1990",
      "gameType": "Shooter / 3rd Person",
      "language": "Japanese",
      "comment": "good",
      "timesPlayed": "0",
      "paramMode": "1",
      "players": "2P sim"
    }
  ]
}