{
  "versionInfo": {
    "ROM DataFile JSON Version": "1.0"
  },
  "romdata": [
    {
      "name": "Mighty! Pang (Euro 000925)",
      "mameName": "mpangr1",
      "parentName": "mpang",
      "path": "{gamesDir}\\MAME\\ROMS\\mpang.7z",
      "emulatorName": "Mame64 Win32",
      "companyName": "Mitchell (Capcom license)",
      "year": "2000",
      "gameType": "Shooter / 3rd Person",
      "language": "English",
      "comment": "good",
      "timesPlayed": "0",
      "paramMode": "1",
      "players": "2P sim"
    },
    {
      "name": "Mystic Warriors (ver JAA)",
      "mameName": "mystwarrj",
      "parentName": "mystwarr",
      "path": "{gamesDir}\\MAME\\ROMS\\mystwarr.7z",
      "emulatorName": "Mame64 Win32",
      "companyName": "Konami",
      "year": "1993",
      "gameType": "Fighter / 2D",
      "language": "English",
      "comment": "imperfect",
      "timesPlayed": "0",
      "paramMode": "1",
      "players": "4P sim"
    },
    {
      "name": "Night Warriors: Darkstalkers' Revenge (Asia 950302)",
      "mameName": "nwarra",
      "parentName": "nwarr",
      "path": "{gamesDir}\\MAME\\ROMS\\nwarr.7z",
      "emulatorName": "Mame64 Win32",
      "companyName": "Capcom",
      "year": "1995",
      "gameType": "Fighter / Versus",
      "language": "English",
      "comment": "good",
      "timesPlayed": "0",
      "paramMode": "1",
      "players": "2P sim"
    },
    {
      "name": "Super Lucky Roulette",
      "mameName": "roul",
      "path": "{gamesDir}\\MAME\\ROMS\\roul.7z",
      "emulatorName": "Mame64 Win32",
      "companyName": "bootleg",
      "year": "1990",
      "gameType": "Casino / Roulette",
      "language": "English",
      "comment": "imperfect",
      "timesPlayed": "0",
      "paramMode": "1",
      "players": "1P"
    },
    {
      "name": "The Typing of the Dead (Rev A)",
      "mameName": "totd",
      "path": "{gamesDir}\\MAME\\ROMS\\totd.7z",
      "emulatorName": "Mame64 Win32",
      "companyName": "Sega",
      "year": "2000",
      "gameType": "Shooter / Misc.",
      "language": "Korean",
      "comment": "preliminary",
      "timesPlayed": "0",
      "paramMode": "1",
      "players": "2P sim"
    },
    {
      "name": "Trivia Master (set 4)",
      "mameName": "trvmstrc",
      "parentName": "trvmstr",
      "path": "{gamesDir}\\MAME\\ROMS\\trvmstr.7z",
      "emulatorName": "Mame64 Win32",
      "companyName": "Enerdyne Technologies Inc.",
      "year": "1985",
      "gameType": "Quiz / English * Mature *",
      "language": "English",
      "comment": "good",
      "timesPlayed": "0",
      "paramMode": "1",
      "players": "4P alt"
    },
    {
      "name": "Wild Cat 3",
      "mameName": "wcat3",
      "path": "{gamesDir}\\MAME\\ROMS\\wcat3.7z",
      "emulatorName": "Mame64 Win32",
      "companyName": "E.A.I.",
      "year": "198?",
      "gameType": "Casino",
      "language": "English",
      "comment": "preliminary",
      "timesPlayed": "0",
      "paramMode": "1",
      "players": "???"
    },
    {
      "name": "Wolf Fang -Kuhga 2001- (Japan)",
      "mameName": "wolffang",
      "parentName": "rohga",
      "path": "{gamesDir}\\MAME\\ROMS\\rohga.7z",
      "emulatorName": "Mame64 Win32",
      "companyName": "Data East Corporation",
      "year": "1991",
      "gameType": "Platform / Shooter Scrolling",
      "language": "Japanese",
      "comment": "good",
      "timesPlayed": "0",
      "paramMode": "1",
      "players": "2P sim"
    }
  ]
}