{
  "versionInfo": {
    "ROM DataFile JSON Version": "1.0"
  },
  "romdata": [
    {
      "name": "Athena",
      "mameName": "athena",
      "path": "{gamesDir}\\MAME\\ROMS\\athena.7z",
      "emulatorName": "Mame64 Win32",
      "companyName": "SNK",
      "year": "1986",
      "gameType": "Platform / Fighter Scrolling",
      "rating": "30 to 40 (Amendable)",
      "language": "English",
      "comment": "good",
      "timesPlayed": "0",
      "paramMode": "1",
      "players": "2P alt"
    },
    {
      "name": "Psycho Soldier (US)",
      "mameName": "psychos",
      "path": "{gamesDir}\\MAME\\ROMS\\psychos.7z",
      "emulatorName": "Mame64 Win32",
      "companyName": "SNK",
      "year": "1987",
      "gameType": "Platform / Fighter Scrolling",
      "rating": "50 to 60 (Not Good Enough)",
      "language": "English",
      "comment": "good",
      "timesPlayed": "0",
      "paramMode": "1",
      "players": "2P sim"
    }
  ]
}