{
  "versionInfo": {
    "ROM DataFile JSON Version": "1.0"
  },
  "romdata": [
    {
      "name": "Pachinko Gindama Shoubu (Japan)",
      "mameName": "pkgnsh",
      "path": "{gamesDir}\\MAME\\ROMS\\pkgnsh.7z",
      "emulatorName": "Mame64 Win32",
      "companyName": "Nakanihon / Dynax",
      "year": "1998",
      "gameType": "Pinball / Pachinko * Mature *",
      "rating": "50 to 60 (Not Good Enough)",
      "language": "Japanese",
      "comment": "imperfect",
      "timesPlayed": "0",
      "paramMode": "1",
      "players": "1P"
    },
    {
      "name": "Pachinko Gindama Shoubu DX (Japan)",
      "mameName": "pkgnshdx",
      "path": "{gamesDir}\\MAME\\ROMS\\pkgnshdx.7z",
      "emulatorName": "Mame64 Win32",
      "companyName": "Nakanihon / Dynax",
      "year": "1998",
      "gameType": "Pinball / Pachinko * Mature *",
      "rating": "50 to 60 (Not Good Enough)",
      "language": "Japanese",
      "comment": "imperfect",
      "timesPlayed": "0",
      "paramMode": "1",
      "players": "1P"
    }
  ]
}